riposte/__init__.py
riposte/_version.py
riposte/command.py
riposte/exceptions.py
riposte/guides.py
riposte/input_streams.py
riposte/riposte.py
riposte/printer/__init__.py
riposte/printer/mixins.py
riposte/printer/palette.py
riposte/printer/thread.py
riposte-0.5.1.dist-info/LICENSE
riposte-0.5.1.dist-info/METADATA
riposte-0.5.1.dist-info/WHEEL
riposte-0.5.1.dist-info/top_level.txt
riposte-0.5.1.dist-info/RECORD
